quicat/__init__.py
quicat/cli/__init__.py
quicat/cli/app.py
quicat/cli/extract/__init__.py
quicat/cli/extract/barcodes_processor.py
quicat/cli/extract/extractor.py
quicat/cli/extract/pattern_matching.py
quicat/cli/extract/reads_processor_bam.py
quicat/cli/extract/reads_processor_bam_conf.py
quicat/cli/extract/reads_processor_fastq.py
quicat/cli/extract/reads_utils.py
quicat/cli/extract/sequences_collapser.py
quicat/cli/simulation/__init__.py
quicat/cli/simulation/fastq_writer.py
quicat/cli/simulation/simulate_barcodes_bulk_dna.py
quicat/cli/simulation/simulate_clones_sc.py
quicat/cli/simulation/simulator.py
quicat/cli/simulation/simulator_utils.py
quicat/cli/utils/__init__.py
quicat/cli/utils/validate_inputs.py
quicat/cli/utils/validate_reference.py
quicat/plotting/__init__.py
quicat/plotting/_barplot.py
quicat/plotting/_boxplot.py
quicat/plotting/_stacked_barplot.py
quicat/read/__init__.py
quicat/read/read_extract_output.py
quicat/tools/__init__.py
quicat/tools/assign_clones.py
quicat-0.1.2.dist-info/LICENSE
quicat-0.1.2.dist-info/METADATA
quicat-0.1.2.dist-info/WHEEL
quicat-0.1.2.dist-info/entry_points.txt
quicat-0.1.2.dist-info/RECORD
