Metadata-Version: 2.3
Name: quicat
Version: 0.1.2
Summary: QUIck Clonal Analysis Toolkit - quicat
Author: Daniele Lucarelli
Author-email: daniele.lucarelli@tum.de
Requires-Python: >=3.10,<3.13
Classifier: Programming Language :: Python :: 3
Classifier: Programming Language :: Python :: 3.10
Classifier: Programming Language :: Python :: 3.11
Classifier: Programming Language :: Python :: 3.12
Requires-Dist: ahocorasick-rs (==0.22.0)
Requires-Dist: anndata (==0.10.9)
Requires-Dist: click (==8.1.7)
Requires-Dist: cutadapt (==4.9)
Requires-Dist: dnaio (==1.2.3)
Requires-Dist: edlib (==1.3.9.post1)
Requires-Dist: flpc (==0.2.4)
Requires-Dist: igraph (==0.11.6)
Requires-Dist: joblib (==1.4.2)
Requires-Dist: leidenalg (>=0.10.2,<0.11.0)
Requires-Dist: matplotlib (==3.9.2)
Requires-Dist: numpy (==1.26)
Requires-Dist: pandas (==2.2.2)
Requires-Dist: polars (==1.1.0)
Requires-Dist: pyarrow (==17.0.0)
Requires-Dist: pyfastx (==2.1.0)
Requires-Dist: pysam (==0.22.1)
Requires-Dist: pyyaml (==6.0.1)
Requires-Dist: rapidfuzz (==3.9.4)
Requires-Dist: rich (==13.7.1)
Requires-Dist: scanpy (==1.10.3)
Requires-Dist: scikit-learn (==1.5.1)
Requires-Dist: scipy (==1.14.0)
Requires-Dist: seaborn (==0.13.2)
Project-URL: Documentation, https://quicat.readthedocs.io
Project-URL: Repository, https://github.com/theislab/quicat
